LICENSE
MANIFEST.in
README.md
requirements.txt
setup.py
Aduro.egg-info/PKG-INFO
Aduro.egg-info/SOURCES.txt
Aduro.egg-info/dependency_links.txt
Aduro.egg-info/requires.txt
Aduro.egg-info/top_level.txt
aduro/__init__.py
aduro/events.py
aduro/manager.py
aduro/snapshot.py
aduro/store.py