Metadata-Version: 1.0
Name: Aduro
Version: 0.0.1a0
Summary: Progress tracker for Amazon Kindle
Home-page: https://github.com/msuozzo/Aduro
Author: Matthew Suozzo
Author-email: matthew.suozzo@gmail.com
License: MIT
Platform: UNKNOWN
